{"nodes": [{"id": "readout", "label": "readout.py", "file_type": "code", "source_file": "smig\\sensor\\readout.py", "source_location": "L1"}, {"id": "readout_multiaccumsimulator", "label": "MultiAccumSimulator", "file_type": "code", "source_file": "smig\\sensor\\readout.py", "source_location": "L16"}, {"id": "readout_multiaccumsimulator_init", "label": ".__init__()", "file_type": "code", "source_file": "smig\\sensor\\readout.py", "source_location": "L30"}, {"id": "readout_multiaccumsimulator_simulate_ramp", "label": ".simulate_ramp()", "file_type": "code", "source_file": "smig\\sensor\\readout.py", "source_location": "L33"}, {"id": "readout_rationale_1", "label": "smig/sensor/readout.py ======================= MULTIACCUM (up-the-ramp) readout", "file_type": "rationale", "source_file": "smig\\sensor\\readout.py", "source_location": "L1"}, {"id": "readout_rationale_17", "label": "MULTIACCUM (up-the-ramp) readout simulator.      Builds a non-destructive read r", "file_type": "rationale", "source_file": "smig\\sensor\\readout.py", "source_location": "L17"}, {"id": "readout_rationale_34", "label": "Simulate MULTIACCUM ramp readout of a charge image.          Parameters", "file_type": "rationale", "source_file": "smig\\sensor\\readout.py", "source_location": "L34"}, {"id": "readout_rationale_47", "label": "# TODO: Implement physical model \u2014 build up-the-ramp sample cube with", "file_type": "rationale", "source_file": "smig\\sensor\\readout.py", "source_location": "L47"}], "edges": [{"source": "readout", "target": "numpy", "relation": "imports", "confidence": "EXTRACTED", "source_file": "smig\\sensor\\readout.py", "source_location": "L11", "weight": 1.0}, {"source": "readout", "target": "smig_config_schemas", "relation": "imports_from", "confidence": "EXTRACTED", "source_file": "smig\\sensor\\readout.py", "source_location": "L13", "weight": 1.0}, {"source": "readout", "target": "readout_multiaccumsimulator", "relation": "contains", "confidence": "EXTRACTED", "source_file": "smig\\sensor\\readout.py", "source_location": "L16", "weight": 1.0}, {"source": "readout_multiaccumsimulator", "target": "readout_multiaccumsimulator_init", "relation": "method", "confidence": "EXTRACTED", "source_file": "smig\\sensor\\readout.py", "source_location": "L30", "weight": 1.0}, {"source": "readout_multiaccumsimulator", "target": "readout_multiaccumsimulator_simulate_ramp", "relation": "method", "confidence": "EXTRACTED", "source_file": "smig\\sensor\\readout.py", "source_location": "L33", "weight": 1.0}, {"source": "readout_rationale_1", "target": "readout", "relation": "rationale_for", "confidence": "EXTRACTED", "source_file": "smig\\sensor\\readout.py", "source_location": "L1", "weight": 1.0}, {"source": "readout_rationale_17", "target": "readout_multiaccumsimulator", "relation": "rationale_for", "confidence": "EXTRACTED", "source_file": "smig\\sensor\\readout.py", "source_location": "L17", "weight": 1.0}, {"source": "readout_rationale_34", "target": "readout_multiaccumsimulator_simulate_ramp", "relation": "rationale_for", "confidence": "EXTRACTED", "source_file": "smig\\sensor\\readout.py", "source_location": "L34", "weight": 1.0}, {"source": "readout_rationale_47", "target": "readout", "relation": "rationale_for", "confidence": "EXTRACTED", "source_file": "smig\\sensor\\readout.py", "source_location": "L47", "weight": 1.0}]}